odoo/addons/fieldservice_repair_order_template/README.rst
odoo/addons/fieldservice_repair_order_template/__init__.py
odoo/addons/fieldservice_repair_order_template/__manifest__.py
odoo/addons/fieldservice_repair_order_template/i18n/fieldservice_repair_order_template.pot
odoo/addons/fieldservice_repair_order_template/i18n/it.po
odoo/addons/fieldservice_repair_order_template/models/__init__.py
odoo/addons/fieldservice_repair_order_template/models/fsm_order.py
odoo/addons/fieldservice_repair_order_template/models/fsm_template.py
odoo/addons/fieldservice_repair_order_template/readme/CONFIGURE.md
odoo/addons/fieldservice_repair_order_template/readme/CONTRIBUTORS.md
odoo/addons/fieldservice_repair_order_template/readme/DESCRIPTION.md
odoo/addons/fieldservice_repair_order_template/static/description/icon.png
odoo/addons/fieldservice_repair_order_template/static/description/index.html
odoo/addons/fieldservice_repair_order_template/tests/__init__.py
odoo/addons/fieldservice_repair_order_template/tests/test_repair_order_template.py
odoo/addons/fieldservice_repair_order_template/views/fsm_template.xml
odoo_addon_fieldservice_repair_order_template-17.0.1.0.0.4.dist-info/METADATA
odoo_addon_fieldservice_repair_order_template-17.0.1.0.0.4.dist-info/WHEEL
odoo_addon_fieldservice_repair_order_template-17.0.1.0.0.4.dist-info/top_level.txt
odoo_addon_fieldservice_repair_order_template-17.0.1.0.0.4.dist-info/RECORD
